{
	"info": {
		"_postman_id": "a62d02bb-78f2-4c7f-9bad-0caa9dad730e",
		"name": "Cerestats",
		"schema": "https://schema.getpostman.com/json/collection/v2.1.0/collection.json"
	},
	"item": [
		{
			"name": "Add/Update Banner data",
			"request": {
				"method": "POST",
				"header": [
					{
						"key": "X-API-KEY",
						"value": "{x-api-key-goes-here}",
						"type": "text"
					}
				],
				"body": {
					"mode": "raw",
					"raw": "{\n    \"key\" : \"banner\",\n    \"value\": {\n        \"show\": \"true\",\n        \"feedbackPercentage\": \"90\",\n        \"onClickLink\": \"http://cere.network\",\n        \"cereBootcampGraduatesNumber\": \"67\",\n        \"tokensRewarded\": \"95000\"\n    }\n}",
					"options": {
						"raw": {
							"language": "json"
						}
					}
				},
				"url": {
					"raw": "https://api.stats.cere.network/api/v1/edp",
					"protocol": "https",
					"host": [
						"api",
						"stats",
						"cere",
						"network"
					],
					"path": [
						"api",
						"v1",
						"edp"
					]
				}
			},
			"response": []
		},
		{
			"name": "Get Banner data",
			"request": {
				"method": "GET",
				"header": [
					{
						"key": "X-API-KEY",
						"value": "{x-api-key-goes-here}",
						"type": "text"
					}
				],
				"url": {
					"raw": "https://api.stats.cere.network/api/v1/edp/banner",
					"protocol": "https",
					"host": [
						"api",
						"stats",
						"cere",
						"network"
					],
					"path": [
						"api",
						"v1",
						"edp",
						"banner"
					]
				}
			},
			"response": []
		}
	]
}